{
  "schema_version": "1.0",
  "slug": "JapanFG/chochukin-rokin",
  "source_path": "JapanFG/chochukin-rokin.md",
  "url": "https://finwiki.zksc.io/JapanFG/chochukin-rokin",
  "github_url": "https://github.com/jasonhnd/finwiki/blob/main/JapanFG/chochukin-rokin.md",
  "raw_markdown_url": "https://raw.githubusercontent.com/jasonhnd/finwiki/main/JapanFG/chochukin-rokin.md",
  "domain": "JapanFG",
  "title": "中央労働金庫 (Chuo Rokin / Central Labour Bank)",
  "entry_type": "wiki_entry",
  "frontmatter": {
    "title": "中央労働金庫 (Chuo Rokin / Central Labour Bank)",
    "aliases": [
      "Chuo-Rokin",
      "chochukin-rokin",
      "中央ろうきん",
      "中央労金",
      "Chuo Rokin Bank",
      "Central Labour Bank",
      "Central Rokin"
    ],
    "domain": "JapanFG",
    "created": "2026-05-25",
    "last_updated": "2026-05-25",
    "last_tended": "2026-05-25",
    "review_by": "2026-11-21",
    "confidence": "likely",
    "tags": [
      "JapanFG",
      "rokin",
      "cooperative-banking",
      "labour-bank",
      "kanto",
      "operating-company",
      "ja-bank-system-peer"
    ],
    "status": "active",
    "sources": [
      "https://chuo.rokin.com/",
      "https://chuo.rokin.com/about/",
      "https://chuo.rokin.com/aboutus/profile/",
      "https://www.rokinren.com/",
      "https://www.rokinren.com/keieishihyo-suii.html",
      "https://www.fsa.go.jp/menkyo/menkyoj/rokin.xlsx",
      "労働金庫法 (昭和 28 年法律第 227 号)"
    ]
  },
  "summary": "This entry sits under JapanFG index as the largest of the 13 rokin (labour bank) operating companies in Japan, providing the rokin-side operating-company anchor parallel to 京都中央信用金庫 (shinkin) and 大阪商銀信用組合 (shinkumi). Read it against 労働金庫連合会 (Rokinren) for the cooperative-system central institution,",
  "headings": [
    "中央労働金庫 (Chuo Rokin / Central Labour Bank)",
    "Wiki route",
    "TL;DR",
    "1. License / 組織構造",
    "13 労働金庫の構成 ^[extracted]",
    "重要年表 ^[extracted]",
    "主要業務 ^[extracted]",
    "ALM・資金フロー ^[extracted]",
    "規模感 (2025-03 末) ^[extracted]",
    "13 ろうきん内の代表性"
  ],
  "body_links": {
    "wikilinks_count": 13,
    "wikilinks": [
      "JapanFG/INDEX",
      "JapanFG/dic",
      "JapanFG/kyoto-chuo-shinkin",
      "JapanFG/norinchukin",
      "JapanFG/osaka-shinkin",
      "JapanFG/osaka-shogin-shinkumi",
      "JapanFG/rokin-renraku",
      "JapanFG/shinkin-central",
      "JapanFG/yokohama-bank",
      "JapanFG/yokohama-shinkin",
      "JapanFG/zenshin-kumi",
      "banking/cooperative-banking-japan",
      "banking/rokin-bank-registry-japan"
    ],
    "resolved_wikilinks": [
      "https://finwiki.zksc.io/JapanFG/INDEX",
      "https://finwiki.zksc.io/JapanFG/dic",
      "https://finwiki.zksc.io/JapanFG/kyoto-chuo-shinkin",
      "https://finwiki.zksc.io/JapanFG/norinchukin",
      "https://finwiki.zksc.io/JapanFG/osaka-shinkin",
      "https://finwiki.zksc.io/JapanFG/osaka-shogin-shinkumi",
      "https://finwiki.zksc.io/JapanFG/rokin-renraku",
      "https://finwiki.zksc.io/JapanFG/shinkin-central",
      "https://finwiki.zksc.io/JapanFG/yokohama-bank",
      "https://finwiki.zksc.io/JapanFG/yokohama-shinkin",
      "https://finwiki.zksc.io/JapanFG/zenshin-kumi",
      "https://finwiki.zksc.io/banking/cooperative-banking-japan",
      "https://finwiki.zksc.io/banking/rokin-bank-registry-japan"
    ],
    "external_links_count": 0,
    "external_links": []
  },
  "metrics": {
    "nonspace_chars": 5737,
    "word_like_tokens": 936,
    "inbound_wikilinks_count": 1,
    "last_modified": "2026-05-29"
  }
}
