{
  "schema_version": "1.0",
  "slug": "systems/cross-chain-four-poles-overview",
  "source_path": "systems/cross-chain-four-poles-overview.md",
  "url": "https://finwiki.zksc.io/systems/cross-chain-four-poles-overview",
  "github_url": "https://github.com/jasonhnd/finwiki/blob/main/systems/cross-chain-four-poles-overview.md",
  "raw_markdown_url": "https://raw.githubusercontent.com/jasonhnd/finwiki/main/systems/cross-chain-four-poles-overview.md",
  "domain": "systems",
  "title": "クロスチェーン 4 極アーキテクチャ · LayerZero / CCIP / Wormhole / Hyperlane + CCTP V2",
  "entry_type": "wiki_entry",
  "frontmatter": {
    "title": "クロスチェーン 4 極アーキテクチャ · LayerZero / CCIP / Wormhole / Hyperlane + CCTP V2 第 5 極",
    "aliases": [
      "cross chain four poles overview",
      "cross-chain interoperability poles",
      "LayerZero CCIP Wormhole Hyperlane"
    ],
    "domain": "systems",
    "created": "2026-05-18",
    "last_updated": "2026-05-26",
    "last_tended": "2026-05-26",
    "review_by": "2026-11-18",
    "confidence": "certain",
    "tags": [
      "systems",
      "cross-chain",
      "bridge",
      "layerzero",
      "ccip",
      "wormhole",
      "hyperlane",
      "cctp"
    ],
    "status": "candidate",
    "sources": [],
    "canonical_anchor": null,
    "related": [],
    "note": null,
    "type": null,
    "entity_node": null,
    "entity_edges": []
  },
  "summary": "This entry sits under systems index. Read it against クロスチェーン選定意思決定ツリー · 主役次元でプロトコルをマッチング for peer / contrast context and fintech index for the broader system / regulatory boundary.",
  "headings": [
    "クロスチェーン 4 極アーキテクチャ · LayerZero / CCIP / Wormhole / Hyperlane + CCTP V2",
    "Wiki route",
    "Key facts",
    "Mechanism / How it works",
    "Origin & evolution",
    "Related",
    "Sources"
  ],
  "body_links": {
    "wikilinks_count": 10,
    "wikilinks": [
      "INDEX",
      "exchanges/cross-chain-bridge-cex-deposit-withdrawal",
      "fintech/INDEX",
      "fintech/onchain-finance-vs-crypto-bifurcation",
      "fintech/usd-stablecoin-interchange",
      "systems/INDEX",
      "systems/cross-chain-five-pole-comparison-matrix",
      "systems/cross-chain-four-poles-ccip-institutional",
      "systems/cross-chain-four-poles-selection-decision",
      "systems/threshold-bft-consensus-rust-implementations"
    ],
    "resolved_wikilinks": [
      "https://finwiki.zksc.io/INDEX",
      "https://finwiki.zksc.io/exchanges/cross-chain-bridge-cex-deposit-withdrawal",
      "https://finwiki.zksc.io/fintech/INDEX",
      "https://finwiki.zksc.io/fintech/onchain-finance-vs-crypto-bifurcation",
      "https://finwiki.zksc.io/fintech/usd-stablecoin-interchange",
      "https://finwiki.zksc.io/systems/INDEX",
      "https://finwiki.zksc.io/systems/cross-chain-five-pole-comparison-matrix",
      "https://finwiki.zksc.io/systems/cross-chain-four-poles-ccip-institutional",
      "https://finwiki.zksc.io/systems/cross-chain-four-poles-selection-decision",
      "https://finwiki.zksc.io/systems/threshold-bft-consensus-rust-implementations"
    ],
    "external_links_count": 0,
    "external_links": []
  },
  "metrics": {
    "nonspace_chars": 3262,
    "word_like_tokens": 523,
    "inbound_wikilinks_count": 19,
    "last_modified": "2026-05-29"
  }
}
