{
  "schema_version": "1.0",
  "slug": "trust-banks/mizuho-trust-bank-detail",
  "source_path": "trust-banks/mizuho-trust-bank-detail.md",
  "url": "https://finwiki.zksc.io/trust-banks/mizuho-trust-bank-detail",
  "github_url": "https://github.com/jasonhnd/finwiki/blob/main/trust-banks/mizuho-trust-bank-detail.md",
  "raw_markdown_url": "https://raw.githubusercontent.com/jasonhnd/finwiki/main/trust-banks/mizuho-trust-bank-detail.md",
  "domain": "trust-banks",
  "title": "みずほ信託銀行 事業詳細 (Mizuho Trust & Banking Operating Profile)",
  "entry_type": "wiki_entry",
  "frontmatter": {
    "title": "みずほ信託銀行 事業詳細 (Mizuho Trust & Banking Operating Profile)",
    "aliases": [
      "Mizuho Trust & Banking Operating Profile",
      "みずほ信託銀行事業詳細",
      "みずほ信託 operating",
      "Mizuho Trust Bank Detail",
      "Mizuho Trust Detail"
    ],
    "domain": "trust-banks",
    "created": "2026-05-25",
    "last_updated": "2026-05-25",
    "last_tended": "2026-05-25",
    "review_by": "2026-11-25",
    "confidence": "likely",
    "tags": [
      "JapanFG",
      "banking",
      "trust-bank",
      "mizuho",
      "operating-profile",
      "pension",
      "real-estate",
      "edinet"
    ],
    "status": "active",
    "sources": [
      "https://www.mizuho-tb.co.jp/company/about/",
      "https://www.mizuho-tb.co.jp/company/about/info.html",
      "https://disclosure2.edinet-fsa.go.jp/",
      "https://www.fsa.go.jp/menkyo/menkyoj/ginkou.xlsx"
    ]
  },
  "summary": "This entry sits under trust-banks INDEX and complements the company-level summary at みずほ信託銀行. Read it against 三菱UFJ信託銀行 (MUTB) / 三井住友信託銀行 for peer trust-bank competitor context, みずほFG / みずほ銀行 for parent-group sister context, and banking index for the broader system / regulatory boundary.",
  "headings": [
    "みずほ信託銀行 事業詳細 (Mizuho Trust & Banking Operating Profile)",
    "Wiki route",
    "TL;DR",
    "1. 親グループ関係（みずほ FG）",
    "2. 法人沿革",
    "3. ライセンス・規制境界",
    "4. 事業セグメント詳細",
    "4.1 年金信託・年金運用",
    "4.2 不動産信託・不動産仲介",
    "4.3 証券代行（株主名簿管理）"
  ],
  "body_links": {
    "wikilinks_count": 10,
    "wikilinks": [
      "banking/INDEX",
      "megabanks/mizuho-bank",
      "megabanks/mizuho-fg",
      "megabanks/mufg",
      "securities-firms/mizuho-securities",
      "trust-banks/INDEX",
      "trust-banks/mitsubishi-ufj-trust-bank",
      "trust-banks/mizuho-trust-bank",
      "trust-banks/smbc-trust-bank",
      "trust-banks/sumitomo-mitsui-trust"
    ],
    "resolved_wikilinks": [
      "https://finwiki.zksc.io/banking/INDEX",
      "https://finwiki.zksc.io/megabanks/mizuho-bank",
      "https://finwiki.zksc.io/megabanks/mizuho-fg",
      "https://finwiki.zksc.io/megabanks/mufg",
      "https://finwiki.zksc.io/securities-firms/mizuho-securities",
      "https://finwiki.zksc.io/trust-banks/INDEX",
      "https://finwiki.zksc.io/trust-banks/mitsubishi-ufj-trust-bank",
      "https://finwiki.zksc.io/trust-banks/mizuho-trust-bank",
      "https://finwiki.zksc.io/trust-banks/smbc-trust-bank",
      "https://finwiki.zksc.io/trust-banks/sumitomo-mitsui-trust"
    ],
    "external_links_count": 0,
    "external_links": []
  },
  "metrics": {
    "nonspace_chars": 5045,
    "word_like_tokens": 759,
    "inbound_wikilinks_count": 1,
    "last_modified": "2026-06-06"
  }
}
