{
  "schema_version": "1.0",
  "slug": "trust-banks/mizuho-trust-bank",
  "source_path": "trust-banks/mizuho-trust-bank.md",
  "url": "https://finwiki.zksc.io/trust-banks/mizuho-trust-bank",
  "github_url": "https://github.com/jasonhnd/finwiki/blob/main/trust-banks/mizuho-trust-bank.md",
  "raw_markdown_url": "https://raw.githubusercontent.com/jasonhnd/finwiki/main/trust-banks/mizuho-trust-bank.md",
  "domain": "trust-banks",
  "title": "みずほ信託銀行 (Mizuho Trust & Banking)",
  "entry_type": "wiki_entry",
  "frontmatter": {
    "title": "みずほ信託銀行 (Mizuho Trust & Banking)",
    "aliases": [
      "Mizuho Trust",
      "Mizuho Trust & Banking",
      "みずほ信託銀行",
      "みずほ信託銀行株式会社",
      "trust-banks/mizuho-trust-banking"
    ],
    "domain": "trust-banks",
    "created": "2026-05-20",
    "last_updated": "2026-06-05",
    "last_tended": "2026-06-05",
    "review_by": "2026-11-20",
    "confidence": "likely",
    "tags": [
      "JapanFG",
      "bank",
      "trust-bank",
      "mizuho",
      "operating-company"
    ],
    "status": "active",
    "sources": [
      "https://www.fsa.go.jp/menkyo/menkyoj/ginkou.xlsx",
      "https://www.mizuho-tb.co.jp/company/about/info.html",
      "https://www.mizuho-tb.co.jp/company/about/info02.html"
    ],
    "canonical_anchor": null,
    "related": [],
    "note": null,
    "type": null,
    "entity_node": null,
    "entity_edges": []
  },
  "summary": "This entry sits under trust-banks INDEX (its domain route). Read it against 三菱UFJ信託銀行 (MUTB) and 三井住友信託銀行 (SMTB) for peer / contrast (the other megabank-group trust banks), and against the FSA plus banking for the supervisory / system boundary. The commercial-bank sibling in the same group is みずほ銀行.",
  "headings": [
    "みずほ信託銀行 (Mizuho Trust & Banking)",
    "Wiki route",
    "TL;DR",
    "1. License / group boundary",
    "2. Operating model",
    "3. Why this page matters",
    "Related",
    "Sources"
  ],
  "body_links": {
    "wikilinks_count": 11,
    "wikilinks": [
      "INDEX",
      "asset-managers/asset-management-one",
      "banking/INDEX",
      "financial-regulators/fsa",
      "megabanks/mizuho-bank",
      "megabanks/mizuho-fg",
      "securities-firms/mizuho-securities",
      "trust-banks/INDEX",
      "trust-banks/master-trust-bank",
      "trust-banks/mitsubishi-ufj-trust-bank",
      "trust-banks/smtb"
    ],
    "resolved_wikilinks": [
      "https://finwiki.zksc.io/INDEX",
      "https://finwiki.zksc.io/asset-managers/asset-management-one",
      "https://finwiki.zksc.io/banking/INDEX",
      "https://finwiki.zksc.io/financial-regulators/fsa",
      "https://finwiki.zksc.io/megabanks/mizuho-bank",
      "https://finwiki.zksc.io/megabanks/mizuho-fg",
      "https://finwiki.zksc.io/securities-firms/mizuho-securities",
      "https://finwiki.zksc.io/trust-banks/INDEX",
      "https://finwiki.zksc.io/trust-banks/master-trust-bank",
      "https://finwiki.zksc.io/trust-banks/mitsubishi-ufj-trust-bank",
      "https://finwiki.zksc.io/trust-banks/smtb"
    ],
    "external_links_count": 0,
    "external_links": []
  },
  "metrics": {
    "nonspace_chars": 2539,
    "word_like_tokens": 358,
    "inbound_wikilinks_count": 25,
    "last_modified": "2026-06-05"
  }
}
