{
  "schema_version": "1.0",
  "slug": "finance/fire-math-reverse-derivation",
  "source_path": "finance/fire-math-reverse-derivation.md",
  "url": "https://finwiki.zksc.io/finance/fire-math-reverse-derivation",
  "github_url": "https://github.com/jasonhnd/finwiki/blob/main/finance/fire-math-reverse-derivation.md",
  "raw_markdown_url": "https://raw.githubusercontent.com/jasonhnd/finwiki/main/finance/fire-math-reverse-derivation.md",
  "domain": "finance",
  "title": "FIRE 数学逆算フレームワーク",
  "entry_type": "wiki_entry",
  "frontmatter": {
    "title": "FIRE 数学逆算フレームワーク",
    "aliases": [],
    "domain": "finance",
    "created": "2026-04-20",
    "last_updated": "2026-05-26",
    "last_tended": "2026-05-26",
    "review_by": "2026-10-30",
    "confidence": "certain",
    "tags": [
      "fire",
      "personal-finance",
      "retirement",
      "safe-withdrawal-rate"
    ],
    "status": "confirmed",
    "sources": [
      "Cooley, Hubbard, and Walz, 1998 Trinity Study on retirement spending.",
      "William Bengen, public safe-withdrawal-rate research.",
      "Public FIRE community materials on withdrawal-rate arithmetic."
    ]
  },
  "summary": "This entry sits under finance index. Read it against Japan IB league table for peer / contrast context and securities index for the broader system / regulatory boundary.",
  "headings": [
    "FIRE 数学逆算フレームワーク",
    "Wiki route",
    "中核命題",
    "標準パラメータ",
    "4ステップの逆算フロー",
    "数学検証式",
    "ギャップ分析",
    "「単純な貯金」モデルとの本質的違い",
    "安全マージン意識",
    "適用境界"
  ],
  "body_links": {
    "wikilinks_count": 5,
    "wikilinks": [
      "INDEX",
      "finance/INDEX",
      "finance/japan-ib-league-table",
      "finance/multi-jurisdiction-identity-tax-leverage",
      "securities/INDEX"
    ],
    "resolved_wikilinks": [
      "https://finwiki.zksc.io/INDEX",
      "https://finwiki.zksc.io/finance/INDEX",
      "https://finwiki.zksc.io/finance/japan-ib-league-table",
      "https://finwiki.zksc.io/finance/multi-jurisdiction-identity-tax-leverage",
      "https://finwiki.zksc.io/securities/INDEX"
    ],
    "external_links_count": 0,
    "external_links": []
  },
  "metrics": {
    "nonspace_chars": 2577,
    "word_like_tokens": 423,
    "inbound_wikilinks_count": 2,
    "last_modified": "2026-05-26"
  }
}
