{
  "schema_version": "1.0",
  "slug": "leasing-firms/orix-corp",
  "source_path": "leasing-firms/orix-corp.md",
  "url": "https://finwiki.zksc.io/leasing-firms/orix-corp",
  "github_url": "https://github.com/jasonhnd/finwiki/blob/main/leasing-firms/orix-corp.md",
  "raw_markdown_url": "https://raw.githubusercontent.com/jasonhnd/finwiki/main/leasing-firms/orix-corp.md",
  "domain": "leasing-firms",
  "title": "オリックス株式会社 (ORIX Corporation)",
  "entry_type": "wiki_entry",
  "frontmatter": {
    "title": "オリックス株式会社 (ORIX Corporation)",
    "aliases": [
      "ORIX",
      "オリックス",
      "オリックス株式会社",
      "ORIX Corporation",
      "旧オリエント・リース"
    ],
    "domain": "leasing-firms",
    "created": "2026-05-19",
    "last_updated": "2026-05-26",
    "last_tended": "2026-05-26",
    "review_by": "2026-11-15",
    "confidence": "likely",
    "tags": [
      "JapanFG",
      "leasing",
      "conglomerate-finance"
    ],
    "status": "active",
    "sources": [
      "Wikipedia: オリックス (企業) (2026-05-19 抽出)",
      "ORIX 第 62 期 (2025-03 期) 有価証券報告書 (2025-06 公表)",
      "ORIX 公式 IR・沿革 (2025 年度更新)"
    ],
    "canonical_anchor": null,
    "related": [],
    "note": null,
    "type": null,
    "entity_node": null,
    "entity_edges": []
  },
  "summary": "This entry sits under leasing-firms INDEX. Read it against 東京センチュリー株式会社 (Tokyo Century Corporation) for peer / contrast context and banking index for the broader system / regulatory boundary.",
  "headings": [
    "オリックス株式会社 (ORIX Corporation)",
    "Wiki route",
    "TL;DR",
    "1. 会社概要",
    "経営体制（2025 年度）^[extracted]",
    "主要株主（2025-03-31 時点）^[extracted]",
    "主要子会社・持分",
    "重要年表（抜粋）^[extracted]",
    "2. 事業セグメント・マップ（10 セグメント）",
    "多角化モデル"
  ],
  "body_links": {
    "wikilinks_count": 10,
    "wikilinks": [
      "banking/INDEX",
      "leasing-firms/INDEX",
      "leasing-firms/fuyo-lease",
      "leasing-firms/mitsubishi-hc-capital",
      "leasing-firms/ntt-tc-lease",
      "leasing-firms/tokyo-century",
      "megabanks/mizuho-fg",
      "megabanks/mufg",
      "megabanks/ndfg",
      "megabanks/smfg"
    ],
    "resolved_wikilinks": [
      "https://finwiki.zksc.io/banking/INDEX",
      "https://finwiki.zksc.io/leasing-firms/INDEX",
      "https://finwiki.zksc.io/leasing-firms/fuyo-lease",
      "https://finwiki.zksc.io/leasing-firms/mitsubishi-hc-capital",
      "https://finwiki.zksc.io/leasing-firms/ntt-tc-lease",
      "https://finwiki.zksc.io/leasing-firms/tokyo-century",
      "https://finwiki.zksc.io/megabanks/mizuho-fg",
      "https://finwiki.zksc.io/megabanks/mufg",
      "https://finwiki.zksc.io/megabanks/ndfg",
      "https://finwiki.zksc.io/megabanks/smfg"
    ],
    "external_links_count": 0,
    "external_links": []
  },
  "metrics": {
    "nonspace_chars": 4680,
    "word_like_tokens": 788,
    "inbound_wikilinks_count": 34,
    "last_modified": "2026-06-08"
  }
}
