{
  "schema_version": "1.0",
  "slug": "regional-banks/hokkoku-fhd",
  "source_path": "regional-banks/hokkoku-fhd.md",
  "url": "https://finwiki.zksc.io/regional-banks/hokkoku-fhd",
  "github_url": "https://github.com/jasonhnd/finwiki/blob/main/regional-banks/hokkoku-fhd.md",
  "raw_markdown_url": "https://raw.githubusercontent.com/jasonhnd/finwiki/main/regional-banks/hokkoku-fhd.md",
  "domain": "regional-banks",
  "title": "北國 FHD (Hokkoku FHD)",
  "entry_type": "wiki_entry",
  "frontmatter": {
    "title": "北國 FHD (Hokkoku FHD)",
    "aliases": [
      "Hokkoku FHD",
      "Hokkoku Financial Holdings",
      "北國フィナンシャルホールディングス",
      "株式会社北國フィナンシャルホールディングス"
    ],
    "domain": "regional-banks",
    "created": "2026-05-19",
    "last_updated": "2026-05-26",
    "last_tended": "2026-05-26",
    "review_by": "2026-11-15",
    "confidence": "likely",
    "tags": [
      "JapanFG",
      "regional-bank",
      "digital-leader",
      "historical-bridge"
    ],
    "status": "borderline",
    "sources": [
      "Wikipedia: 北國フィナンシャルホールディングス (公開情報)",
      "Wikipedia: 北國銀行 (公開情報)",
      "北國 FHD 公式 IR 公開資料",
      "https://www.ccig.co.jp/company/about/",
      "https://www.fsa.go.jp/menkyo/menkyoj/ginkoumochikabu.pdf"
    ]
  },
  "summary": "This entry sits under JapanFG index. Read it against ふくおか FG (FFG) for peer / contrast context and banking index for the broader system / regulatory boundary.",
  "headings": [
    "北國 FHD (Hokkoku FHD)",
    "Wiki route",
    "Overview",
    "1. 会社概要",
    "主要子会社・持分",
    "2. 合併・沿革",
    "3. 事業セグメント・マップ",
    "「地銀発デジタルプラットフォーマー」志向",
    "Microsoft 長期提携",
    "競合・参照対象"
  ],
  "body_links": {
    "wikilinks_count": 14,
    "wikilinks": [
      "JapanFG/INDEX",
      "banking/INDEX",
      "banking/minna-bank-baas-model",
      "concordia-fg",
      "financial-regulators/cci-group",
      "fukuoka-fg",
      "hokuhoku-fg",
      "mebuki-fg",
      "mizuho-fg",
      "mufg",
      "regional-banks/fukuoka-fg",
      "sbi-hd",
      "shizuoka-fg",
      "smfg"
    ],
    "resolved_wikilinks": [
      "https://finwiki.zksc.io/JapanFG/INDEX",
      "https://finwiki.zksc.io/banking/INDEX",
      "https://finwiki.zksc.io/banking/minna-bank-baas-model",
      "https://finwiki.zksc.io/concordia-fg",
      "https://finwiki.zksc.io/financial-regulators/cci-group",
      "https://finwiki.zksc.io/fukuoka-fg",
      "https://finwiki.zksc.io/hokuhoku-fg",
      "https://finwiki.zksc.io/mebuki-fg",
      "https://finwiki.zksc.io/mizuho-fg",
      "https://finwiki.zksc.io/mufg",
      "https://finwiki.zksc.io/regional-banks/fukuoka-fg",
      "https://finwiki.zksc.io/sbi-hd",
      "https://finwiki.zksc.io/shizuoka-fg",
      "https://finwiki.zksc.io/smfg"
    ],
    "external_links_count": 0,
    "external_links": []
  },
  "metrics": {
    "nonspace_chars": 4272,
    "word_like_tokens": 675,
    "inbound_wikilinks_count": 5,
    "last_modified": "2026-06-04"
  }
}
