{
  "schema_version": "1.0",
  "slug": "fintech/japan-stablecoin-regulatory-landscape",
  "source_path": "fintech/japan-stablecoin-regulatory-landscape.md",
  "url": "https://finwiki.zksc.io/fintech/japan-stablecoin-regulatory-landscape",
  "github_url": "https://github.com/jasonhnd/finwiki/blob/main/fintech/japan-stablecoin-regulatory-landscape.md",
  "raw_markdown_url": "https://raw.githubusercontent.com/jasonhnd/finwiki/main/fintech/japan-stablecoin-regulatory-landscape.md",
  "domain": "fintech",
  "title": "日本 Stablecoin 法制度の三層構造（JPYC・USDC・Project Pax）",
  "entry_type": "wiki_entry",
  "frontmatter": {
    "title": "日本 Stablecoin 法制度の三層構造（JPYC・USDC・Project Pax）",
    "aliases": [
      "Japan stablecoin regulatory landscape",
      "日本ステーブルコイン制度",
      "JPYC USDC Progmat",
      "fintech/japan-stablecoin-and-crypto-regulation"
    ],
    "domain": "fintech",
    "created": "2026-04-14",
    "last_updated": "2026-05-21",
    "last_tended": "2026-05-21",
    "review_by": "2026-10-30",
    "confidence": "likely",
    "tags": [
      "fintech",
      "stablecoin",
      "JapanFG",
      "EPI"
    ],
    "status": "confirmed",
    "sources": [
      "https://www.fsa.go.jp/menkyo/menkyoj/denshikessaisyudan.xlsx",
      "https://www.fsa.go.jp/menkyo/menkyoj/shikin_idou.pdf",
      "https://jpyc.co.jp/",
      "https://www.sbivc.co.jp/usdc",
      "https://progmat.co.jp/about/",
      "https://progmat.co.jp/concept/"
    ]
  },
  "summary": "Stablecoin coverage in this wiki should route as follows:",
  "headings": [
    "日本 Stablecoin 法制度の三層構造（JPYC・USDC・Project Pax）",
    "Current map (source-refresh 2026-05-21)",
    "Implication",
    "Related"
  ],
  "body_links": {
    "wikilinks_count": 10,
    "wikilinks": [
      "INDEX",
      "exchanges/jp-exchange-jpyc",
      "exchanges/jp-exchange-sbi-vc-trade",
      "fintech/ai-payment-two-tracks",
      "fintech/gold-tokenization-scheme-comparison",
      "fintech/japan-ecisb-license",
      "fintech/japan-financial-regulation",
      "fintech/jp-stablecoin-progmat",
      "payment-firms/jpyc",
      "payment-firms/progmat"
    ],
    "resolved_wikilinks": [
      "https://finwiki.zksc.io/INDEX",
      "https://finwiki.zksc.io/exchanges/jp-exchange-jpyc",
      "https://finwiki.zksc.io/exchanges/jp-exchange-sbi-vc-trade",
      "https://finwiki.zksc.io/fintech/ai-payment-two-tracks",
      "https://finwiki.zksc.io/fintech/gold-tokenization-scheme-comparison",
      "https://finwiki.zksc.io/fintech/japan-ecisb-license",
      "https://finwiki.zksc.io/fintech/japan-financial-regulation",
      "https://finwiki.zksc.io/fintech/jp-stablecoin-progmat",
      "https://finwiki.zksc.io/payment-firms/jpyc",
      "https://finwiki.zksc.io/payment-firms/progmat"
    ],
    "external_links_count": 0,
    "external_links": []
  },
  "metrics": {
    "nonspace_chars": 2443,
    "word_like_tokens": 379,
    "inbound_wikilinks_count": 177,
    "last_modified": "2026-06-04"
  }
}
